aim_spacy/__init__.py
aim_spacy/aim_displacy.py
aim_spacy/base_logger.py
aim_spacy/displacy_wrapper.py
aim_spacy/handler.py
aim_spacy/types.py
aim_spacy/utils.py
aim_spacy-0.2.0.dist-info/LICENSE
aim_spacy-0.2.0.dist-info/METADATA
aim_spacy-0.2.0.dist-info/WHEEL
aim_spacy-0.2.0.dist-info/entry_points.txt
aim_spacy-0.2.0.dist-info/top_level.txt
aim_spacy-0.2.0.dist-info/RECORD
